waveglow/LICENSE
waveglow/README.md
waveglow/convert_model.py
waveglow/denoiser.py
waveglow/distributed.py
waveglow/glow.py
waveglow/glow_old.py
waveglow/inference.py
waveglow/mel2samp.py
waveglow/train.py
waveglow/waveglow_logo.png
waveglow-22.12.28.dist-info/entry_points.txt
waveglow-22.12.28.dist-info/METADATA
waveglow-22.12.28.dist-info/WHEEL
waveglow-22.12.28.dist-info/RECORD
